inconnu/__init__.py
inconnu/config.py
inconnu/exceptions.py
inconnu/model_installer.py
inconnu/nlp/entity_redactor.py
inconnu/nlp/interfaces.py
inconnu/nlp/patterns.py
inconnu/nlp/utils.py
inconnu-0.1.1.dist-info/METADATA
inconnu-0.1.1.dist-info/WHEEL
inconnu-0.1.1.dist-info/entry_points.txt
inconnu-0.1.1.dist-info/licenses/LICENSE
inconnu-0.1.1.dist-info/RECORD
