Metadata-Version: 2.4
Name: inconnu
Version: 0.1.1
Summary: GDPR-compliant data privacy tool for entity redaction and de-anonymization
Project-URL: Homepage, https://github.com/0xjgv/inconnu
Project-URL: Documentation, https://github.com/0xjgv/inconnu#readme
Project-URL: Repository, https://github.com/0xjgv/inconnu
Project-URL: Issues, https://github.com/0xjgv/inconnu/issues
Author-email: 0xjgv <juans.gaitan@gmail.com>
License: MIT
License-File: LICENSE
Keywords: anonymization,gdpr,nlp,pii,privacy,pseudonymization,redaction,spacy
Classifier: Development Status :: 4 - Beta
Classifier: Intended Audience :: Developers
Classifier: Intended Audience :: Healthcare Industry
Classifier: Intended Audience :: Legal Industry
Classifier: License :: OSI Approved :: MIT License
Classifier: Operating System :: OS Independent
Classifier: Programming Language :: Python :: 3
Classifier: Programming Language :: Python :: 3.10
Classifier: Programming Language :: Python :: 3.11
Classifier: Programming Language :: Python :: 3.12
Classifier: Topic :: Security
Classifier: Topic :: Software Development :: Libraries :: Python Modules
Classifier: Topic :: Text Processing :: Linguistic
Requires-Python: >=3.10
Requires-Dist: phonenumbers>=9.0.8
Requires-Dist: spacy>=3.8.7
